nevergrad/__init__.py
nevergrad/benchmark/__init__.py
nevergrad/benchmark/__main__.py
nevergrad/benchmark/core.py
nevergrad/benchmark/execution.py
nevergrad/benchmark/experiments.py
nevergrad/benchmark/exporttable.py
nevergrad/benchmark/frozenexperiments.py
nevergrad/benchmark/gymexperiments.py
nevergrad/benchmark/optgroups.py
nevergrad/benchmark/plotting.py
nevergrad/benchmark/test_core.py
nevergrad/benchmark/test_execution.py
nevergrad/benchmark/test_experiments.py
nevergrad/benchmark/test_plotting.py
nevergrad/benchmark/test_utils.py
nevergrad/benchmark/test_xpbase.py
nevergrad/benchmark/utils.py
nevergrad/benchmark/xpbase.py
nevergrad/common/__init__.py
nevergrad/common/decorators.py
nevergrad/common/errors.py
nevergrad/common/sphere.py
nevergrad/common/test_decorators.py
nevergrad/common/test_testing.py
nevergrad/common/test_tools.py
nevergrad/common/testing.py
nevergrad/common/tools.py
nevergrad/common/typing.py
nevergrad/functions/__init__.py
nevergrad/functions/base.py
nevergrad/functions/corefuncs.py
nevergrad/functions/functionlib.py
nevergrad/functions/helpers.py
nevergrad/functions/pbt.py
nevergrad/functions/test_base.py
nevergrad/functions/test_corefuncs.py
nevergrad/functions/test_functionlib.py
nevergrad/functions/test_utils.py
nevergrad/functions/utils.py
nevergrad/functions/ac/__init__.py
nevergrad/functions/ac/ac.py
nevergrad/functions/ac/test_ac.py
nevergrad/functions/arcoating/__init__.py
nevergrad/functions/arcoating/core.py
nevergrad/functions/arcoating/test_core.py
nevergrad/functions/control/__init__.py
nevergrad/functions/control/core.py
nevergrad/functions/control/mujoco.py
nevergrad/functions/control/test_mujoco.py
nevergrad/functions/cycling/__init__.py
nevergrad/functions/cycling/cycling.py
nevergrad/functions/cycling/cyclist.py
nevergrad/functions/cycling/mensteampursuit.py
nevergrad/functions/cycling/simulationresult.py
nevergrad/functions/cycling/teampursuit.py
nevergrad/functions/cycling/test_cycling.py
nevergrad-1.0.12.dist-info/LICENSE
nevergrad-1.0.12.dist-info/METADATA
nevergrad-1.0.12.dist-info/WHEEL
nevergrad-1.0.12.dist-info/top_level.txt
nevergrad-1.0.12.dist-info/RECORD
